django_api_explorer/__init__.py
django_api_explorer/cli.py
django_api_explorer/core/__init__.py
django_api_explorer/core/comprehensive_method_detector.py
django_api_explorer/core/data_factory.py
django_api_explorer/core/formatter.py
django_api_explorer/core/method_detector.py
django_api_explorer/core/models.py
django_api_explorer/core/settings_loader.py
django_api_explorer/core/url_extractor.py
django_api_explorer/utils/__init__.py
django_api_explorer/utils/path_utils.py
django_api_explorer/web/__init__.py
django_api_explorer/web/enhanced_server.py
django_api_explorer/web/file_watcher_server.py
django_api_explorer/web/static/css/style.css
django_api_explorer/web/static/js/main.js
django_api_explorer/web/templates/enhanced_index.html
django_api_explorer-1.0.4.dist-info/licenses/LICENSE
django_api_explorer-1.0.4.dist-info/METADATA
django_api_explorer-1.0.4.dist-info/WHEEL
django_api_explorer-1.0.4.dist-info/entry_points.txt
django_api_explorer-1.0.4.dist-info/top_level.txt
django_api_explorer-1.0.4.dist-info/RECORD
