Metadata-Version: 2.4
Name: django_api_explorer
Version: 1.0.4
Summary: A powerful command-line tool and web interface for discovering, documenting, and testing API endpoints in Django projects
Author-email: Vikas Gole <vikasgole089@gmail.com>
License: MIT
Project-URL: Homepage, https://github.com/SketchG2001/api-explorer
Project-URL: Repository, https://github.com/SketchG2001/api-explorer
Project-URL: Issues, https://github.com/SketchG2001/api-explorer/issues
Keywords: django,api,documentation,discovery,endpoints
Classifier: Development Status :: 5 - Production/Stable
Classifier: Intended Audience :: Developers
Classifier: License :: OSI Approved :: MIT License
Classifier: Programming Language :: Python :: 3
Classifier: Programming Language :: Python :: 3.9
Classifier: Programming Language :: Python :: 3.9
Classifier: Programming Language :: Python :: 3.10
Classifier: Programming Language :: Python :: 3.11
Classifier: Framework :: Django
Classifier: Topic :: Software Development :: Documentation
Classifier: Topic :: Internet :: WWW/HTTP :: HTTP Servers
Requires-Python: >=3.9
License-File: LICENSE
Requires-Dist: django<5.0,>=3.2
Requires-Dist: click>=8.0.0
Requires-Dist: rich>=12.0.0
Requires-Dist: watchdog>=3.0.0
Provides-Extra: drf
Requires-Dist: djangorestframework>=3.12.0; extra == "drf"
Provides-Extra: dev
Requires-Dist: pytest>=7.0.0; extra == "dev"
Requires-Dist: pytest-django>=4.5.0; extra == "dev"
Requires-Dist: pytest-cov>=4.0.0; extra == "dev"
Requires-Dist: black>=22.0.0; extra == "dev"
Requires-Dist: mypy>=1.0.0; extra == "dev"
Requires-Dist: isort>=5.0.0; extra == "dev"
Requires-Dist: bandit>=1.7.0; extra == "dev"
Requires-Dist: safety>=2.0.0; extra == "dev"
Requires-Dist: twine>=4.0.0; extra == "dev"
Requires-Dist: build>=0.10.0; extra == "dev"
Dynamic: license-file
